goat_plugins/debridge/__init__.py
goat_plugins/debridge/parameters.py
goat_plugins/debridge/service.py
goat_sdk_plugin_debridge-0.1.0.dist-info/METADATA
goat_sdk_plugin_debridge-0.1.0.dist-info/WHEEL
goat_sdk_plugin_debridge-0.1.0.dist-info/RECORD
